{"school":"국립창원대학교(남해캠퍼스)","years":[2026],"nodes":[[2026,"관광융합학부","자연과학","자연과학",3,0,["관광융합학부 원예조경과","관광융합학부 항공호텔관광과","관광융합학부 호텔조리제빵경영과"],0],[2026,"에너지안전융합학부","공학","공학",1,0,[],0],[2026,"항공해양방산학부","공학","공학",2,0,["항공해양방산학부 방산기계AI과","항공해양방산학부 항공정비과"],0]],"links":[],"deaths":{"2026":[{"dept":"금융회계사무과","broad":"인문사회"},{"dept":"금융회계사무과","broad":"인문사회"},{"dept":"로컬푸드전공","broad":"자연과학"},{"dept":"산업안전관리과","broad":"공학"},{"dept":"산업안전관리과","broad":"공학"},{"dept":"소프트웨어공학과","broad":"공학"},{"dept":"원예조경과","broad":"공학"},{"dept":"원예조경과","broad":"공학"},{"dept":"전기・자동차계열","broad":"공학"},{"dept":"전기・자동차계열","broad":"공학"},{"dept":"항공기계전공","broad":"공학"},{"dept":"항공운항과","broad":"인문사회"},{"dept":"항공정비과","broad":"공학"},{"dept":"항공정비전공","broad":"공학"},{"dept":"항공정비학부","broad":"공학"},{"dept":"항공제작정비전공","broad":"공학"},{"dept":"호텔관광전공","broad":"인문사회"},{"dept":"호텔조리전공","broad":"자연과학"},{"dept":"호텔조리전공","broad":"자연과학"},{"dept":"힐링관광전공","broad":"인문사회"}]},"bands":[],"base2014":0}