{"school":"한북대학교","years":[2014,2015,2016,2017,2018,2019,2020],"nodes":[],"links":[],"deaths":{"2014":[{"dept":"간호학과","broad":"자연과학"},{"dept":"건강관리학과","broad":"예체능"},{"dept":"경영학과","broad":"인문사회"},{"dept":"국제관광경영학과","broad":"인문사회"},{"dept":"국제통상학과","broad":"인문사회"},{"dept":"레저스포츠학과","broad":"예체능"},{"dept":"멀티미디어디자인학과","broad":"예체능"},{"dept":"사회복지학과","broad":"인문사회"},{"dept":"식품영양학과","broad":"자연과학"},{"dept":"에너지자원학과","broad":"공학"},{"dept":"영어학과","broad":"인문사회"},{"dept":"영유아보육학과","broad":"인문사회"},{"dept":"중국어학과","broad":"인문사회"},{"dept":"컴퓨터정보학과","broad":"공학"},{"dept":"특허법률학과","broad":"인문사회"}],"2015":[{"dept":"간호학과","broad":"자연과학"},{"dept":"건강관리학과","broad":"예체능"},{"dept":"경영학과","broad":"인문사회"},{"dept":"국제관광경영학과","broad":"인문사회"},{"dept":"국제통상학과","broad":"인문사회"},{"dept":"레저스포츠학과","broad":"예체능"},{"dept":"멀티미디어디자인학과","broad":"예체능"},{"dept":"사회복지학과","broad":"인문사회"},{"dept":"식품영양학과","broad":"자연과학"},{"dept":"에너지자원학과","broad":"공학"},{"dept":"영어학과","broad":"인문사회"},{"dept":"영유아보육학과","broad":"인문사회"},{"dept":"중국어학과","broad":"인문사회"},{"dept":"컴퓨터정보학과","broad":"공학"},{"dept":"특허법률학과","broad":"인문사회"}],"2016":[{"dept":"간호학과","broad":"자연과학"},{"dept":"건강관리학과","broad":"예체능"},{"dept":"경영학과","broad":"인문사회"},{"dept":"국제관광경영학과","broad":"인문사회"},{"dept":"국제통상학과","broad":"인문사회"},{"dept":"레저스포츠학과","broad":"예체능"},{"dept":"멀티미디어디자인학과","broad":"예체능"},{"dept":"사회복지학과","broad":"인문사회"},{"dept":"식품영양학과","broad":"자연과학"},{"dept":"에너지자원학과","broad":"공학"},{"dept":"영어학과","broad":"인문사회"},{"dept":"영유아보육학과","broad":"인문사회"},{"dept":"중국어학과","broad":"인문사회"},{"dept":"컴퓨터정보학과","broad":"공학"},{"dept":"특허법률학과","broad":"인문사회"}],"2017":[{"dept":"간호학과","broad":"자연과학"},{"dept":"건강관리학과","broad":"예체능"},{"dept":"경영학과","broad":"인문사회"},{"dept":"국제관광경영학과","broad":"인문사회"},{"dept":"국제통상학과","broad":"인문사회"},{"dept":"레저스포츠학과","broad":"예체능"},{"dept":"멀티미디어디자인학과","broad":"예체능"},{"dept":"사회복지학과","broad":"인문사회"},{"dept":"식품영양학과","broad":"자연과학"},{"dept":"에너지자원학과","broad":"공학"},{"dept":"영어학과","broad":"인문사회"},{"dept":"영유아보육학과","broad":"인문사회"},{"dept":"중국어학과","broad":"인문사회"},{"dept":"컴퓨터정보학과","broad":"공학"},{"dept":"특허법률학과","broad":"인문사회"}],"2018":[{"dept":"간호학과","broad":"자연과학"},{"dept":"국제통상학과","broad":"인문사회"},{"dept":"사회복지학과","broad":"인문사회"},{"dept":"경영학과","broad":"인문사회"},{"dept":"영유아보육학과","broad":"인문사회"},{"dept":"국제관광경영학과","broad":"인문사회"},{"dept":"특허법률학과","broad":"인문사회"},{"dept":"멀티미디어디자인학과","broad":"예체능"},{"dept":"에너지자원학과","broad":"공학"},{"dept":"컴퓨터정보학과","broad":"공학"},{"dept":"식품영양학과","broad":"자연과학"},{"dept":"중국어학과","broad":"인문사회"},{"dept":"영어학과","broad":"인문사회"},{"dept":"건강관리학과","broad":"예체능"},{"dept":"레저스포츠학과","broad":"예체능"}],"2019":[{"dept":"간호학과","broad":"자연과학"},{"dept":"경영학과","broad":"인문사회"},{"dept":"국제관광경영학과","broad":"인문사회"},{"dept":"국제통상학과","broad":"인문사회"},{"dept":"사회복지학과","broad":"인문사회"},{"dept":"영유아보육학과","broad":"인문사회"},{"dept":"특허법률학과","broad":"인문사회"},{"dept":"멀티미디어디자인학과","broad":"예체능"},{"dept":"식품영양학과","broad":"자연과학"},{"dept":"에너지자원학과","broad":"공학"},{"dept":"컴퓨터정보학과","broad":"공학"},{"dept":"영어학과","broad":"인문사회"},{"dept":"중국어학과","broad":"인문사회"},{"dept":"건강관리학과","broad":"예체능"},{"dept":"레저스포츠학과","broad":"예체능"}],"2020":[{"dept":"간호학과","broad":"자연과학"},{"dept":"경영학과","broad":"인문사회"},{"dept":"국제관광경영학과","broad":"인문사회"},{"dept":"국제통상학과","broad":"인문사회"},{"dept":"사회복지학과","broad":"인문사회"},{"dept":"영유아보육학과","broad":"인문사회"},{"dept":"특허법률학과","broad":"인문사회"},{"dept":"멀티미디어디자인학과","broad":"예체능"},{"dept":"식품영양학과","broad":"자연과학"},{"dept":"에너지자원학과","broad":"공학"},{"dept":"컴퓨터정보학과","broad":"공학"},{"dept":"영어학과","broad":"인문사회"},{"dept":"중국어학과","broad":"인문사회"},{"dept":"건강관리학과","broad":"예체능"},{"dept":"레저스포츠학과","broad":"예체능"}]},"bands":[],"base2014":0}