{"sub":"광고・홍보학","broad":"인문사회","years":[2019,2020,2021,2022,2023,2024,2025,2026],"nodes":[[2019,"광고홍보","광고・홍보학","인문사회",3,0,["가톨릭관동대학교","대구가톨릭대학교","한신대학교"],0],[2019,"광고홍보이벤트학","광고・홍보학","인문사회",2,0,["신경주대학교","우석대학교"],0],[2019,"광고홍보학","광고・홍보학","인문사회",17,0,["경성대학교","계명대학교","고신대학교","국민대학교","남서울대학교","동국대학교","동명대학교","동의대학교","서원대학교","세명대학교"],0],[2020,"광고홍보","광고・홍보학","인문사회",3,4,["가톨릭관동대학교","대구가톨릭대학교","한신대학교"],0],[2020,"광고홍보이벤트학","광고・홍보학","인문사회",2,0,["신경주대학교","우석대학교"],0],[2020,"광고홍보학","광고・홍보학","인문사회",18,0,["경성대학교","계명대학교","고신대학교","국민대학교","남서울대학교","동국대학교","동명대학교","동서대학교","동의대학교","서원대학교"],0],[2021,"광고홍보","광고・홍보학","인문사회",3,0,["대구가톨릭대학교","목원대학교","한신대학교"],0],[2021,"광고홍보이벤트학","광고・홍보학","인문사회",1,8,["우석대학교"],0],[2021,"광고홍보학","광고・홍보학","인문사회",18,2,["가톨릭관동대학교","경성대학교","계명대학교","고신대학교","국민대학교","남서울대학교","동국대학교","동명대학교","동서대학교","동의대학교"],0],[2022,"광고홍보","광고・홍보학","인문사회",2,0,["대구가톨릭대학교","한신대학교"],0],[2022,"광고홍보학","광고・홍보학","인문사회",17,4,["가톨릭관동대학교","경성대학교","계명대학교","고신대학교","국민대학교","남서울대학교","동국대학교","동서대학교","동의대학교","서원대학교"],0],[2023,"광고홍보","광고・홍보학","인문사회",3,6,["대구가톨릭대학교","신라대학교","한신대학교"],0],[2023,"광고홍보학","광고・홍보학","인문사회",16,0,["가톨릭관동대학교","경성대학교","계명대학교","국민대학교","남서울대학교","동국대학교","동서대학교","동의대학교","서원대학교","세명대학교"],0],[2024,"광고홍보","광고・홍보학","인문사회",1,0,["대구가톨릭대학교"],0],[2024,"광고홍보학","광고・홍보학","인문사회",18,2,["가톨릭관동대학교","경성대학교","계명대학교","국민대학교","남서울대학교","동국대학교","동명대학교","동서대학교","동의대학교","서원대학교"],0],[2025,"광고홍보","광고・홍보학","인문사회",1,0,["대구가톨릭대학교"],0],[2025,"광고홍보학","광고・홍보학","인문사회",18,0,["가톨릭관동대학교","경성대학교","계명대학교","국민대학교","남서울대학교","동국대학교","동명대학교","동서대학교","동의대학교","서원대학교"],0],[2026,"광고홍보","광고・홍보학","인문사회",1,0,["대구가톨릭대학교"],0],[2026,"광고홍보학","광고・홍보학","인문사회",17,0,["가톨릭관동대학교","경성대학교","계명대학교","국민대학교","남서울대학교","동국대학교","동명대학교","동서대학교","동의대학교","서원대학교"],0]],"links":[[0,3,0,0,0,3],[3,8,3,0,0,1],[8,10,0,0,0,17],[10,12,0,0,0,15],[12,14,0,0,0,16],[14,16,0,0,0,18],[16,18,0,0,0,18],[2,5,0,0,0,17],[5,8,0,0,0,17],[1,4,0,0,0,2],[3,6,0,0,0,2],[6,9,0,0,0,2],[9,11,0,0,0,2],[11,13,0,0,0,1],[13,15,0,0,0,1],[15,17,0,0,0,1],[10,11,3,0,0,1],[11,14,3,0,0,1],[4,7,0,0,0,1]]}