{"sub":"인류학","broad":"인문사회","years":[2014,2015,2016,2017,2018,2019,2020,2021,2022,2023,2024,2025],"nodes":[[2014,"문화인류학과","인류학","인문사회",5,0,["강원대학교","국립목포대학교","덕성여자대학교","연세대학교","영남대학교"],0],[2014,"인류학과","인류학","인문사회",2,0,["서울대학교","전남대학교"],0],[2015,"문화인류학과","인류학","인문사회",5,0,["강원대학교","국립목포대학교","덕성여자대학교","연세대학교","영남대학교"],0],[2015,"인류학과","인류학","인문사회",2,0,["서울대학교","전남대학교"],0],[2016,"문화인류학과","인류학","인문사회",4,0,["강원대학교","덕성여자대학교","연세대학교","영남대학교"],0],[2016,"인류학과","인류학","인문사회",1,0,["서울대학교"],0],[2017,"문화인류학과","인류학","인문사회",3,0,["강원대학교","덕성여자대학교","연세대학교"],0],[2017,"인류학과","인류학","인문사회",1,0,["서울대학교"],0],[2018,"문화인류학과","인류학","인문사회",3,0,["강원대학교","덕성여자대학교","연세대학교"],0],[2018,"인류학과","인류학","인문사회",1,0,["서울대학교"],0],[2019,"문화인류학과","인류학","인문사회",3,4,["강원대학교","덕성여자대학교","연세대학교"],0],[2019,"인류학과","인류학","인문사회",1,0,["서울대학교"],0],[2020,"문화인류학과","인류학","인문사회",2,0,["강원대학교","연세대학교"],0],[2020,"문화인류학전공","인류학","인문사회",1,3,["덕성여자대학교"],0],[2020,"인류학과","인류학","인문사회",1,0,["서울대학교"],0],[2021,"문화인류학과","인류학","인문사회",2,0,["강원대학교","연세대학교"],0],[2021,"문화인류학전공","인류학","인문사회",1,0,["덕성여자대학교"],0],[2021,"인류학과","인류학","인문사회",1,0,["서울대학교"],0],[2022,"문화인류학과","인류학","인문사회",2,0,["강원대학교","연세대학교"],0],[2022,"문화인류학전공","인류학","인문사회",1,0,["덕성여자대학교"],0],[2022,"인류학과","인류학","인문사회",1,0,["서울대학교"],0],[2023,"문화인류학과","인류학","인문사회",2,0,["강원대학교","연세대학교"],0],[2023,"문화인류학전공","인류학","인문사회",1,0,["덕성여자대학교"],0],[2023,"인류학과","인류학","인문사회",1,0,["서울대학교"],0],[2024,"문화인류학과","인류학","인문사회",2,0,["강원대학교","연세대학교"],0],[2024,"문화인류학전공","인류학","인문사회",1,0,["덕성여자대학교"],0],[2024,"인류학과","인류학","인문사회",1,0,["서울대학교"],0],[2025,"문화인류학과","인류학","인문사회",2,0,["강원대학교","연세대학교"],0],[2025,"문화인류학전공","인류학","인문사회",1,0,["덕성여자대학교"],0],[2025,"인류학과","인류학","인문사회",1,0,["서울대학교"],0]],"links":[[0,2,0,0,0,5],[2,4,0,0,0,4],[4,6,0,0,0,4],[6,8,0,0,0,3],[8,10,0,0,0,3],[10,12,0,0,0,2],[12,15,0,0,0,2],[15,18,0,0,0,2],[18,21,0,0,0,2],[21,24,0,0,0,2],[24,27,0,0,0,2],[10,13,3,0,0,1],[13,16,0,0,0,1],[16,19,0,0,0,1],[19,22,0,0,0,1],[22,25,0,0,0,1],[25,28,0,0,0,1],[1,3,0,0,0,2],[3,5,0,0,0,1],[5,7,0,0,0,1],[7,9,0,0,0,1],[9,11,0,0,0,1],[11,14,0,0,0,1],[14,17,0,0,0,1],[17,20,0,0,0,1],[20,23,0,0,0,1],[23,26,0,0,0,1],[26,29,0,0,0,1]]}